marisa_bindings/__init__.py
marisa_bindings/_marisa.cpython-310-darwin.so
marisa_bindings/marisa.py
marisa_bindings-1.0.0.dist-info/LICENSE
marisa_bindings-1.0.0.dist-info/METADATA
marisa_bindings-1.0.0.dist-info/WHEEL
marisa_bindings-1.0.0.dist-info/top_level.txt
marisa_bindings-1.0.0.dist-info/RECORD
