Metadata-Version: 2.1
Name: marisa-bindings
Version: 1.0.0
Summary: An unofficial project that provides Python bindings for the MARISA Trie, which is implemented in C++ using SWIG.
Author-email: Nobuyuki Sekimori <43375309+juno-rmks@users.noreply.github.com>
License: BSD 2-Clause License
Project-URL: Source Code, https://github.com/juno-rmks/marisa-bindings/
Project-URL: Issue Tracker, https://github.com/juno-rmks/marisa-bindings/issues/
Project-URL: Documentation, https://marisa-bindings.readthedocs.io/
Classifier: License :: OSI Approved :: BSD License
Classifier: Operating System :: OS Independent
Classifier: Programming Language :: C++
Classifier: Programming Language :: Python
Requires-Python: >=3.10
License-File: LICENSE
Provides-Extra: dev
Requires-Dist: build ; extra == 'dev'
Requires-Dist: twine ; extra == 'dev'
Requires-Dist: pylint ; extra == 'dev'
Requires-Dist: black ; extra == 'dev'
Requires-Dist: isort ; extra == 'dev'
Requires-Dist: marisa-bindings[doc,test] ; extra == 'dev'
Provides-Extra: doc
Requires-Dist: Sphinx ==5.3.0 ; extra == 'doc'
Requires-Dist: sphinx-intl ==2.1.0 ; extra == 'doc'
Requires-Dist: sphinx-rtd-theme ==1.2.0 ; extra == 'doc'
Requires-Dist: myst-parser ==1.0.0 ; extra == 'doc'
Provides-Extra: test
Requires-Dist: pytest ; extra == 'test'
Requires-Dist: coverage ; extra == 'test'
Requires-Dist: pytest-benchmark ; extra == 'test'
Requires-Dist: pytest-mock ; extra == 'test'
